dark_mode_switch/__init__.py
dark_mode_switch/static/dark_mode_switch/dark-mode-switch.css
dark_mode_switch/static/dark_mode_switch/dark-mode-switch.js
dark_mode_switch/templates/dark_mode_switch/dark_mode_switch.html
django_bootstrap5_dark_mode_switch-0.2.2.dist-info/LICENSE
django_bootstrap5_dark_mode_switch-0.2.2.dist-info/METADATA
django_bootstrap5_dark_mode_switch-0.2.2.dist-info/WHEEL
django_bootstrap5_dark_mode_switch-0.2.2.dist-info/top_level.txt
django_bootstrap5_dark_mode_switch-0.2.2.dist-info/RECORD
