Metadata-Version: 2.1
Name: django-bootstrap5-dark-mode-switch
Version: 0.2.2
Summary: Dark mode switch for Django with Bootstrap 5
Home-page: https://github.com/christianwgd/django-bootstrap5-dark-mode-switch
Author: Christian Wiegand
License: MIT
Keywords: django,bootstrap,dark mode
Classifier: Programming Language :: Python :: 3
Classifier: License :: OSI Approved :: MIT License
Classifier: Operating System :: OS Independent
Requires-Python: >=3.10
License-File: LICENSE
Requires-Dist: django>=4.2
Requires-Dist: django-bootstrap5>=24.2
